moldy/__init__.py
moldy/__main__.py
moldy/logging.py
moldy/molding.py
moldy/terminal_formatting.py
moldy-2025.3.8.dist-info/METADATA
moldy-2025.3.8.dist-info/WHEEL
moldy-2025.3.8.dist-info/entry_points.txt
moldy-2025.3.8.dist-info/licenses/LICENSE.txt
moldy-2025.3.8.dist-info/RECORD
