Metadata-Version: 2.4
Name: Moldy
Version: 2025.3.8
Summary: I needed a quick templating engine for generating translated versions of files
Author: Günthner
License-File: LICENSE.txt
Keywords: Template Engine
Classifier: Environment :: Console
Classifier: License :: OSI Approved :: MIT License
Classifier: Operating System :: OS Independent
Classifier: Programming Language :: Python :: 3
Requires-Python: >=3.8
